[
  {
    "_id": "2",
    "email": "laura.bianchi@test.it",
    "password": "$2a$12$3JT6DaKyrB7ctrQvY6OFEe11028WPD3jDsFrz28QfTDZ19ZLNPrqq",
    "firstName": "Laura",
    "lastName": "Bianchi",
    "userType": "architect",
    "orderNumber": "5678",
    "phone": "+39 0934 654321",
    "language": "it",
    "isVerified": true,
    "activationToken": "TOKEN-ARCH-5678-2025",
    "settings": {
      "notifications": true,
      "emailNotifications": false,
      "theme": "light",
      "language": "it",
      "privacy": {
        "showEmail": false,
        "showPhone": true,
        "showProjects": true
      }
    },
    "createdAt": "2024-02-20T00:00:00.000Z",
    "isActive": true,
    "lastLogin": "2026-03-03T16:48:51.772Z",
    "updatedAt": "2026-03-03T17:12:45.868Z",
    "emailVerified": true,
    "passwordResetToken": null,
    "passwordResetExpires": null
  },
  {
    "_id": "3",
    "email": "giuseppe.verdi@test.it",
    "password": "$2a$12$IgsXH.kKcqhvZTH2akDF0e4HkgzvI0oh0/b.Fx.iGRdmJALHiAH/q",
    "firstName": "Giuseppe",
    "lastName": "Verdi",
    "userType": "architect",
    "phone": "+39 333 123456788",
    "language": "en",
    "isVerified": true,
    "settings": {
      "notifications": true,
      "emailNotifications": true,
      "theme": "dark",
      "language": "en",
      "privacy": {
        "showEmail": true,
        "showPhone": true,
        "showProjects": true
      }
    },
    "createdAt": "2024-03-10T00:00:00.000Z",
    "isActive": true,
    "lastLogin": "2026-03-03T01:55:49.098Z",
    "updatedAt": "2026-03-03T01:55:49.098Z",
    "orderNumber": "1234"
  }
]